{"chunk_definitions":[{"chunk_id":"cy86u7pfb3tdk","chunk_label":"kebutuhan library","document_id":"A8BA6C22","expansion_state":0,"options":{"engine":"r","label":"kebutuhan library","message":false,"results":"hide","warning":false},"row":24,"row_count":1,"visible":true},{"chunk_id":"csetup_chunk","chunk_label":"setup","document_id":"A8BA6C22","expansion_state":0,"options":{"engine":"r","include":false,"label":"setup","message":false,"results":"hide","warning":false},"row":30,"row_count":1,"visible":true},{"chunk_id":"chwzhg561ojlb","chunk_label":"save generated playlist data to .csv file","document_id":"A8BA6C22","expansion_state":0,"options":{"engine":"r","eval":false,"label":"save generated playlist data to .csv file"},"row":111,"row_count":1,"visible":true},{"chunk_id":"cqvmd94oy6en2","chunk_label":"load csv file","document_id":"A8BA6C22","expansion_state":0,"options":{"engine":"r","label":"load csv file"},"row":117,"row_count":1,"visible":true},{"chunk_id":"co3t2qij102v5","chunk_label":"data description","document_id":"A8BA6C22","expansion_state":0,"options":{"engine":"r","label":"data description"},"row":123,"row_count":1,"visible":true},{"chunk_id":"coi1ilcr5dm3t","chunk_label":"statistic description","document_id":"A8BA6C22","expansion_state":0,"options":{"engine":"r","label":"statistic description"},"row":129,"row_count":1,"visible":true},{"chunk_id":"cwxrz2e17zub8","chunk_label":"remove unnecessary column","document_id":"A8BA6C22","expansion_state":0,"options":{"engine":"r","label":"remove unnecessary column"},"row":139,"row_count":1,"visible":true},{"chunk_id":"cyhzfvuptirbh","chunk_label":"check for missing value","document_id":"A8BA6C22","expansion_state":0,"options":{"engine":"r","label":"check for missing value"},"row":145,"row_count":1,"visible":true},{"chunk_id":"c8lrdz9e793s4","chunk_label":"milliseconds to seconds","document_id":"A8BA6C22","expansion_state":0,"options":{"engine":"r","label":"milliseconds to seconds"},"row":154,"row_count":1,"visible":true},{"chunk_id":"ckfupqlclydni","chunk_label":"convert loudness value to positive","document_id":"A8BA6C22","expansion_state":0,"options":{"engine":"r","label":"convert loudness value to positive"},"row":160,"row_count":1,"visible":true},{"chunk_id":"coe9aporb86l6","chunk_label":"shuffle dataset","document_id":"A8BA6C22","expansion_state":0,"options":{"engine":"r","label":"shuffle dataset"},"row":169,"row_count":1,"visible":true},{"chunk_id":"csjlm0qu12bzf","chunk_label":"danceability","document_id":"A8BA6C22","expansion_state":0,"options":{"engine":"r","label":"danceability"},"row":183,"row_count":1,"visible":true},{"chunk_id":"crut2xmr37oo4","chunk_label":"energy","document_id":"A8BA6C22","expansion_state":0,"options":{"engine":"r","label":"energy"},"row":197,"row_count":1,"visible":true},{"chunk_id":"ceo2uhh3bpfmh","chunk_label":"key","document_id":"A8BA6C22","expansion_state":0,"options":{"engine":"r","fig.height":7,"label":"key"},"row":226,"row_count":1,"visible":true},{"chunk_id":"cp00viisejmb7","chunk_label":"unnamed-chunk-1","document_id":"A8BA6C22","expansion_state":0,"options":{"engine":"r","label":"loudness"},"row":240,"row_count":1,"visible":true},{"chunk_id":"cb1k6g2k1ob64","chunk_label":"unnamed-chunk-2","document_id":"A8BA6C22","expansion_state":0,"options":{"engine":"r","label":"mode"},"row":257,"row_count":1,"visible":true},{"chunk_id":"ctkze7teejmg2","chunk_label":"unnamed-chunk-3","document_id":"A8BA6C22","expansion_state":0,"options":{"engine":"r","label":"speechiness"},"row":271,"row_count":1,"visible":true},{"chunk_id":"cpxtjahpgwg41","chunk_label":"unnamed-chunk-4","document_id":"A8BA6C22","expansion_state":0,"options":{"engine":"r","label":"acousticness"},"row":285,"row_count":1,"visible":true},{"chunk_id":"c2c8jju982r60","chunk_label":"unnamed-chunk-5","document_id":"A8BA6C22","expansion_state":0,"options":{"engine":"r","label":"instrumentalness"},"row":299,"row_count":1,"visible":true},{"chunk_id":"cyc3mnhn49zy9","chunk_label":"unnamed-chunk-6","document_id":"A8BA6C22","expansion_state":0,"options":{"engine":"r","label":"liveness"},"row":313,"row_count":1,"visible":true},{"chunk_id":"c98vp5omzvcz7","chunk_label":"unnamed-chunk-7","document_id":"A8BA6C22","expansion_state":0,"options":{"engine":"r","label":"valence"},"row":327,"row_count":1,"visible":true},{"chunk_id":"cah16zi44f0lo","chunk_label":"unnamed-chunk-8","document_id":"A8BA6C22","expansion_state":0,"options":{"engine":"r","label":"tempo"},"row":341,"row_count":1,"visible":true},{"chunk_id":"cu3hmr1wlqtaj","chunk_label":"unnamed-chunk-9","document_id":"A8BA6C22","expansion_state":0,"options":{"engine":"r","label":"duration_sec"},"row":355,"row_count":1,"visible":true},{"chunk_id":"cb8ul5wmpbc8k","chunk_label":"unnamed-chunk-10","document_id":"A8BA6C22","expansion_state":0,"options":{"engine":"r","label":"unnamed-chunk-11"},"row":365,"row_count":1,"visible":true},{"chunk_id":"cw1n22idkm1ny","chunk_label":"unnamed-chunk-11","document_id":"A8BA6C22","expansion_state":0,"options":{"engine":"r","label":"unnamed-chunk-33"},"row":391,"row_count":1,"visible":true},{"chunk_id":"c19kts5a9qlov","chunk_label":"unnamed-chunk-12","document_id":"A8BA6C22","expansion_state":0,"options":{"engine":"r","label":"unnamed-chunk-83"},"row":406,"row_count":1,"visible":true},{"chunk_id":"c9f8b7iftz3r6","chunk_label":"unnamed-chunk-13","document_id":"A8BA6C22","expansion_state":0,"options":{"engine":"r","label":"unnamed-chunk-84"},"row":418,"row_count":1,"visible":true},{"chunk_id":"cpe4lnt3pt2mi","chunk_label":"unnamed-chunk-14","document_id":"A8BA6C22","expansion_state":0,"options":{"engine":"r","label":"unnamed-chunk-89"},"row":432,"row_count":1,"visible":true},{"chunk_id":"cqr1eys8b0b94","chunk_label":"unnamed-chunk-15","document_id":"A8BA6C22","expansion_state":0,"options":{"engine":"r","label":"unnamed-chunk-98"},"row":441,"row_count":1,"visible":true},{"chunk_id":"c3hfw5zn4sd1u","chunk_label":"unnamed-chunk-16","document_id":"A8BA6C22","expansion_state":0,"options":{"engine":"r","label":"unnamed-chunk-91"},"row":456,"row_count":1,"visible":true},{"chunk_id":"cmutpyxpe6se5","chunk_label":"unnamed-chunk-17","document_id":"A8BA6C22","expansion_state":0,"options":{"engine":"r","label":"unnamed-chunk-107"},"row":486,"row_count":1,"visible":true},{"chunk_id":"c689rhsv3zd0z","chunk_label":"unnamed-chunk-18","document_id":"A8BA6C22","expansion_state":0,"options":{"engine":"r","label":"unnamed-chunk-108"},"row":492,"row_count":1,"visible":true}],"chunk_rendered_width":683,"default_chunk_options":{"echo":true},"doc_write_time":1591344900,"working_dir":null}